README.rst
setup.py
pelican_delicious/__init__.py
pelican_delicious/plugin.py
pelican_delicious/test_plugin.py
pelican_delicious.egg-info/PKG-INFO
pelican_delicious.egg-info/SOURCES.txt
pelican_delicious.egg-info/dependency_links.txt
pelican_delicious.egg-info/requires.txt
pelican_delicious.egg-info/top_level.txt