Metadata-Version: 1.1
Name: pelican-delicious
Version: 0.0.1
Summary: Easily embed delicious bookmarks in your Pelican articles.
Home-page: https://github.com/2xyo/pelican-delicious
Author: Yohann Lepage
Author-email: yohann@lepage.info
License: BSD
Platform: UNKNOWN
Classifier: Development Status :: 2 - Pre-Alpha
Classifier: Environment :: Console
Classifier: Intended Audience :: Developers
Classifier: License :: BEER-WARE
Classifier: Natural Language :: English
Classifier: Operating System :: OS Independent
Classifier: Programming Language :: Python
Classifier: Programming Language :: Python :: 2.6
Classifier: Programming Language :: Python :: 2.7
Classifier: Programming Language :: Python :: 3
Classifier: Topic :: Internet :: WWW/HTTP
Classifier: Topic :: Software Development :: Libraries :: Python Modules
Classifier: Topic :: Text Processing
